{"_ts":[1498895609,1498939708],"_r":{"breakdown":{"html":{"bytes":[7880,7880],"requests":[1,1]},"js":{"bytes":[0,0],"requests":[0,0]},"css":{"bytes":[0,0],"requests":[0,0]},"image":{"bytes":[0,0],"requests":[0,0]},"flash":{"bytes":[0,0],"requests":[0,0]},"font":{"bytes":[129695,129695],"requests":[3,3]},"other":{"bytes":[1824,1826],"requests":[2,2]}},"date":[1498895609,1498939708],"domElements":[0,0],"domInteractive":[838,1052],"firstPaint":[0,0],"fullyLoaded":[1475,1736],"id":["170701_WW_CSW","170701_P2_XSF"],"loadTime":[1122,1381],"render":[913,1094],"SpeedIndex":[903,1103],"TTFB":[697,849],"videoFrames":[[{"_i":"frame_0000.jpg","_t":0,"_vc":0},{"_i":"frame_0009.jpg","_t":900,"_vc":99},{"_i":"frame_0012.jpg","_t":1200,"_vc":100}],[{"_i":"frame_0000.jpg","_t":0,"_vc":0},{"_i":"frame_0011.jpg","_t":1100,"_vc":99},{"_i":"frame_0014.jpg","_t":1400,"_vc":100}]],"visualComplete":[1200,1400],"lighthouse":[null,null],"pagespeed":[99,99]}}