{"_ts":[1567344735],"_r":{"breakdown":{"html":{"bytes":[6719],"requests":[1]},"js":{"bytes":[0],"requests":[0]},"css":{"bytes":[0],"requests":[0]},"image":{"bytes":[86714],"requests":[3]},"flash":{"bytes":[0],"requests":[0]},"font":{"bytes":[96580],"requests":[3]},"video":{"bytes":[0],"requests":[0]},"other":{"bytes":[527],"requests":[1]}},"date":[1567344735],"domElements":[159],"domInteractive":[870],"firstPaint":[884],"fullyLoaded":[1682],"id":["190901_R1_23fa2f6cec4d46ebf629f9352aa35a1c"],"loadTime":[1555],"render":[900],"SpeedIndex":[913],"TTFB":[797],"videoFrames":[[{"_i":"ms_000000.jpg","_t":0,"_vc":0},{"_i":"ms_000900.jpg","_t":900,"_vc":96},{"_i":"ms_001000.jpg","_t":1000,"_vc":98},{"_i":"ms_001100.jpg","_t":1100,"_vc":98},{"_i":"ms_001200.jpg","_t":1200,"_vc":98},{"_i":"ms_001300.jpg","_t":1300,"_vc":98},{"_i":"ms_001400.jpg","_t":1400,"_vc":99},{"_i":"ms_001500.jpg","_t":1500,"_vc":100}]],"visualComplete":[1500],"lighthouse":[null],"pagespeed":[93]}}